brahma/brahmaLogging.py
brahma/configCore.py
brahma/lib.py
brahma/bots/__init__.py
brahma/bots/bot_root.py
brahma/dna/__init__.py
brahma/dna/vixen_dna.py
brahma/genes/__init__.py
brahma/genes/dnaroot.py
brahma/genome/__init__.py
brahma/genome/transcription.py
brahma/genome/vixen_genome.py
brahma/world/__init__.py
brahma/world/brahma_feed.py
brahma/world/data_bucket.py
brahma/world/environment.py
brahma/world/population.py
brahma/world/simulated_feed.py
brahma-0.1.423.dist-info/LICENSE.txt
brahma-0.1.423.dist-info/METADATA
brahma-0.1.423.dist-info/WHEEL
brahma-0.1.423.dist-info/top_level.txt
brahma-0.1.423.dist-info/RECORD
