Metadata-Version: 2.1
Name: brahma
Version: 0.1.423
Summary: BrahmA Aritificial Intelligence Framework
Home-page: UNKNOWN
Author: Rahul Tandon
Author-email: rahul@vixenintelligence.com
License: UNKNOWN
Platform: UNKNOWN
Classifier: Development Status :: 5 - Production/Stable
Classifier: Programming Language :: Python :: 3
Classifier: License :: OSI Approved :: MIT License
Classifier: Operating System :: OS Independent
Requires-Python: >=3.6
